agileupstate/__init__.py
agileupstate/ansible.py
agileupstate/cli.py
agileupstate/client.py
agileupstate/exceptions.py
agileupstate/state.py
agileupstate/strings.py
agileupstate/terminal.py
agileupstate/vault.py
agileupstate-0.0.44.dist-info/entry_points.txt
agileupstate-0.0.44.dist-info/LICENSE
agileupstate-0.0.44.dist-info/WHEEL
agileupstate-0.0.44.dist-info/METADATA
agileupstate-0.0.44.dist-info/RECORD
