Metadata-Version: 2.1
Name: agileupstate
Version: 0.0.44
Summary: State mangement tool for Future Agile CICD
Home-page: https://github.com/Agile-Solutions-GB-Ltd/agileupstate
License: Apache-2.0
Author: agileturret
Author-email: Paul.Gilligan@agilesolutions.co.uk
Requires-Python: >=3.8,<4.0
Classifier: License :: OSI Approved :: Apache Software License
Classifier: Programming Language :: Python :: 3
Classifier: Programming Language :: Python :: 3.8
Classifier: Programming Language :: Python :: 3.9
Classifier: Programming Language :: Python :: 3.10
Requires-Dist: PyYAML (>=5.4.1,<6.0.0)
Requires-Dist: click (>=8.1,<9.0)
Requires-Dist: hvac (>=1.0.2,<2.0.0)
Requires-Dist: prettytable (>=3.3.0,<4.0.0)
Requires-Dist: pywinrm (>=0.4.3,<0.5.0)
Project-URL: Repository, https://github.com/Agile-Solutions-GB-Ltd/agileupstate.git
